[{"Program Name":"Rush","#":"1","Reg/Tag":"","Chip Name":"Uninstll","Code":"G","Link":"Link to URL"},{"Program Name":"Custom2","#":"2","Reg/Tag":"","Chip Name":"Static","Code":"G","Link":"HP+500"},{"Program Name":"FlotShoe","#":"1","Reg/Tag":"","Chip Name":"BblStar3","Code":"G","Link":"HP+300"},{"Program Name":"SuprArmr","#":"1","Reg/Tag":"","Chip Name":"SloGauge","Code":"*","Link":"HP+50"},{"Program Name":"FstBarr","#":"1","Reg/Tag":"","Chip Name":"ProtoMnSP","Code":"B","Link":"Speed+1"},{"Program Name":"Undersht","#":"1","Reg/Tag":"","Chip Name":"GrndMan","Code":"*","Link":"ChargMAX"},{"#":"3","Chip Name":"AntiDmg","Code":"*"},{"#":"1","Chip Name":"AntiNavi","Code":"*"},{"#":"1","Chip Name":"LifeAur","Code":"U"},{"#":"3","Chip Name":"Invisibl","Code":"*"},{"#":"1","Reg/Tag":"[REG]","Chip Name":"FullCust","Code":"*"},{"Program Name":"CellImage","#":"1","Reg/Tag":"","Chip Name":"SloGauge","Code":"*"},{"#":"2","Chip Name":"GrabBnsh","Code":"B"},{"#":"4","Chip Name":"AreaGrab","Code":"*"},{"#":"2","Chip Name":"PanlGrab","Code":"*"},{"#":"1","Chip Name":"Anubis","Code":"P"},{"#":"1","Chip Name":"WindRack","Code":"*"},{"#":"2","Chip Name":"PoisSeed","Code":"*"},{"#":"2","Chip Name":"MachGun1","Code":"*"}]