[{"Program Name":"Custom1","#":"1","Reg/Tag":"[REG]","Chip Name":"FullCust","Code":"*","Link":"Link to URL"},{"Program Name":"SuprArmr","#":"3","Reg/Tag":"","Chip Name":"Invisibl","Code":"*","Link":"AttckMAX"},{"Program Name":"Rush","#":"3","Reg/Tag":"","Chip Name":"AntiDmg","Code":"*","Link":"ChargMAX"},{"Program Name":"BugStop","#":"4","Reg/Tag":"","Chip Name":"AreaGrab","Code":"*","Link":"HP+500"},{"Program Name":"GigFldr1","#":"1","Reg/Tag":"","Chip Name":"MachGun3","Code":"F"},{"Program Name":"UnderSht","#":"1","Reg/Tag":"","Chip Name":"LifeAur","Code":"U"},{"#":"2","Chip Name":"WindRack","Code":"*"},{"#":"1","Chip Name":"Atk+30","Code":"*"},{"#":"2","Chip Name":"Sensor3","Code":"Q"},{"Program Name":"CellImage","#":"1","Reg/Tag":"","Chip Name":"WhiCapsl","Code":"*"},{"#":"1","Chip Name":"MagCoil","Code":"*"},{"#":"1","Chip Name":"EraseMan","Code":"*"},{"#":"1","Chip Name":"BlastMan","Code":"*"},{"#":"1","Chip Name":"BblWrap","Code":"Q"},{"#":"1","Chip Name":"ElmntMan","Code":"*"},{"#":"1","Chip Name":"TenguMan","Code":"*"},{"#":"1","Chip Name":"FireSwrd","Code":"F"},{"#":"1","Chip Name":"JudgeMan","Code":"*"},{"#":"1","Chip Name":"GrabRvng","Code":"Q"},{"#":"1","Chip Name":"Bass","Code":"F"},{"#":"1","Chip Name":"ColForce","Code":"Q"}]