[{"Program Name":"HP+400","#":"1","Reg/Tag":"","Chip Name":"BblStar3","Code":"G","Link":"image"},{"Program Name":"GigFldr1","#":"2","Reg/Tag":"","Chip Name":"MachGun2","Code":"G"},{"Program Name":"GigFldr1","#":"1","Reg/Tag":"","Chip Name":"WindRack","Code":"*"},{"Program Name":"SuprArmr","#":"1","Reg/Tag":"","Chip Name":"NeoVari","Code":"N"},{"Program Name":"FstBarr","#":"1","Reg/Tag":"","Chip Name":"WoodDrgn","Code":"G"},{"Program Name":"UnderSht","#":"2","Reg/Tag":"","Chip Name":"Recov300","Code":"J"},{"Program Name":"BugStop","#":"5","Reg/Tag":"","Chip Name":"AreaGrab","Code":"*"},{"Program Name":"ChargMAX","#":"1","Reg/Tag":"[REG]","Chip Name":"FullCust","Code":"*"},{"Program Name":"Attack+1","#":"3","Reg/Tag":"","Chip Name":"Invisibl","Code":"*"},{"#":"1","Chip Name":"LifeAur","Code":"U"},{"#":"3","Chip Name":"AntiDmg","Code":"*"},{"#":"1","Chip Name":"Uninstll","Code":"G"},{"Program Name":"CellImage","#":"1","Reg/Tag":"","Chip Name":"GrndManSP","Code":"G"},{"#":"1","Chip Name":"EraseMan","Code":"*"},{"#":"1","Chip Name":"JudgeMan","Code":"*"},{"#":"1","Chip Name":"ElmntMan","Code":"*"},{"#":"1","Chip Name":"ElmntMnSP","Code":"E"},{"#":"1","Chip Name":"BassAnly","Code":"F"},{"#":"1","Chip Name":"MetrKnuk","Code":"N"},{"#":"1","Chip Name":"HubBatc","Code":"J"}]